MANIFEST.in
VERSION
setup.py
amulet/__init__.py
amulet/actions.py
amulet/charm.py
amulet/deployer.py
amulet/helpers.py
amulet/sentry.py
amulet/waiter.py
amulet.egg-info/PKG-INFO
amulet.egg-info/SOURCES.txt
amulet.egg-info/dependency_links.txt
amulet.egg-info/pbr.json
amulet.egg-info/requires.txt
amulet.egg-info/top_level.txt
amulet/unit-scripts/amulet/directory_listing.py
amulet/unit-scripts/amulet/filesystem_data.py
amulet/unit-scripts/amulet/find_python.sh
amulet/unit-scripts/amulet/juju_agent.py
tests/__init__.py
tests/helper.py
tests/test_charm.py
tests/test_deployer.py
tests/test_gitcharm.py
tests/test_helpers.py
tests/test_sentry.py
tests/test_waiter.py
tests/functional/__init__.py
tests/functional/test_sentry.py