Metadata-Version: 1.0
Name: amulet
Version: 1.21.0
Summary: Tools to help with writing Juju Charm Functional tests
Home-page: https://github.com/juju/amulet
Author: Marco Ceppi
Author-email: marco@ceppi.net
License: UNKNOWN
Platform: UNKNOWN
